[
  {
    "source": "Bergen Kunsthall",
    "title": "2026 18 Feb Playdate: Myhr Mobeck Sand / Arin Gran Solo Landmark Concert",
    "url": "https://www.kunsthall.no/en/events/3251-2026-02-18/",
    "city": "Bergen",
    "venue": "Landmark",
    "when": "Wed 20:00",
    "where": "Landmark",
    "tags": [
      "culture"
    ],
    "sources": [
      "Bergen Kunsthall"
    ],
    "starts_at": "2026-02-18T20:00:00+01:00"
  },
  {
    "source": "Bergen Kunsthall",
    "title": "Concert Playdate: Myhr Mobeck Sand / Arin Gran Solo Wed 18 Feb 20:00, Landmark",
    "url": "https://www.kunsthall.no/en/events/3251-2026-02-18/",
    "city": "Bergen",
    "venue": "Landmark",
    "when": "Wed 20:00",
    "where": "Landmark",
    "tags": [
      "culture"
    ],
    "sources": [
      "Bergen Kunsthall"
    ],
    "starts_at": "2026-02-18T20:00:00+01:00"
  }
]
