[
  {
    "source": "Bergen Kunsthall",
    "title": "2026 27 Mar Naoko + Oak Ay Landmark Concert",
    "url": "https://www.kunsthall.no/en/events/3268-2026-03-27/",
    "city": "Bergen",
    "venue": "Landmark",
    "when": "Fri 20:30",
    "where": "Landmark",
    "tags": [
      "culture"
    ],
    "sources": [
      "Bergen Kunsthall"
    ],
    "starts_at": "2026-03-27T20:30:00+01:00"
  },
  {
    "source": "Bergen Kunsthall",
    "title": "Concert Naoko + Oak Ay Fri 27 Mar 20:30, Landmark",
    "url": "https://www.kunsthall.no/en/events/3268-2026-03-27/",
    "city": "Bergen",
    "venue": "Landmark",
    "when": "Fri 20:30",
    "where": "Landmark",
    "tags": [
      "culture"
    ],
    "sources": [
      "Bergen Kunsthall"
    ],
    "starts_at": "2026-03-27T20:30:00+01:00"
  }
]
